ms_autoqc/AcquisitionListener.py
ms_autoqc/AutoQCProcessing.py
ms_autoqc/DashWebApp.py
ms_autoqc/DatabaseFunctions.py
ms_autoqc/PlotGeneration.py
ms_autoqc/SlackNotifications.py
ms_autoqc/__init__.py
ms_autoqc/__main__.py
ms_autoqc/assets/favicon.ico
ms_autoqc/assets/styles.css
ms_autoqc-1.0.1.dist-info/METADATA
ms_autoqc-1.0.1.dist-info/WHEEL
ms_autoqc-1.0.1.dist-info/entry_points.txt
ms_autoqc-1.0.1.dist-info/top_level.txt
ms_autoqc-1.0.1.dist-info/RECORD
