Metadata-Version: 2.1
Name: ms-autoqc
Version: 1.0.1
Summary: Realtime quality control for mass spectrometry data acquisition
Author-email: Wasim Sandhu <wasim.sandhu@czbiohub.org>
Project-URL: Homepage, https://czbiohub.github.io/MS-AutoQC
Keywords: mass-spectrometry,mass-spec,autoqc,mass-spec-quality-control
Classifier: License :: OSI Approved :: MIT License
Classifier: Programming Language :: Python
Classifier: Programming Language :: Python :: 3
Requires-Python: >=3.8
Requires-Dist: pandas (==1.4.2)
Requires-Dist: plotly (==5.6.0)
Requires-Dist: dash (==2.6.1)
Requires-Dist: dash-bootstrap-components (==1.2.1)
Requires-Dist: psutil (==5.9.4)
Requires-Dist: pydrive2 (==1.14.0)
Requires-Dist: slack-sdk (==3.18.1)
Requires-Dist: sqlalchemy (==1.4.32)
Requires-Dist: watchdog (==2.1.9)
Requires-Dist: tomli ; python_version <= "3.11"
Provides-Extra: dev
